.coveragerc
.gitignore
.pylintrc
.readthedocs.yml
.style.yapf
.travis.yml
CHEATSHEET.rst
LICENSE
LICENSE.APACHE2
LICENSE.MIT
MANIFEST.in
Makefile
README.rst
pyproject.toml
setup.cfg
setup.py
asyncgpio/__init__.py
asyncgpio/gpio.py
asyncgpio/libgpiod.py
asyncgpio/test.py
asyncgpio.egg-info/PKG-INFO
asyncgpio.egg-info/SOURCES.txt
asyncgpio.egg-info/dependency_links.txt
asyncgpio.egg-info/requires.txt
asyncgpio.egg-info/top_level.txt
ci/rtd-requirements.txt
ci/test-requirements.txt
ci/travis.sh
docs/Makefile
docs/make.bat
docs/source/conf.py
docs/source/history.rst
docs/source/index.rst
docs/source/usage.rst
docs/source/_static/.gitkeep
examples/line_echo.py
examples/line_echo_polled.py
examples/line_value.py
examples/push_button_event.py
newsfragments/.gitkeep
newsfragments/README.rst
tests/__init__.py
tests/run.py
tests/test.sh